moma/__init__.py
moma-0.0.0.dist-info/METADATA
moma-0.0.0.dist-info/RECORD
moma-0.0.0.dist-info/WHEEL
moma-0.0.0.dist-info/top_level.txt
