Metadata-Version: 2.1
Name: moma
Version: 0.0.0
Summary: moma
Home-page: https://github.com/xiaomi-automl/moma
Author: Bo Zhang
Author-email: zhangbo11@xiaomi.com
License: UNKNOWN
Platform: UNKNOWN
Classifier: Programming Language :: Python :: 3
Classifier: License :: OSI Approved :: MIT License
Classifier: Operating System :: OS Independent
Requires-Python: >=3.6
